storage/__init__.py
storage/cloudfiles_storage.py
storage/ftp_storage.py
storage/google_storage.py
storage/local_storage.py
storage/py.typed
storage/retry.py
storage/s3_storage.py
storage/storage.py
storage/swift_storage.py
storage/url_parser.py
object_storage-0.15.2.dist-info/LICENSE
object_storage-0.15.2.dist-info/METADATA
object_storage-0.15.2.dist-info/WHEEL
object_storage-0.15.2.dist-info/RECORD
