Metadata-Version: 2.1
Name: object-storage
Version: 0.15.2
Summary: Python library for accessing files over various file transfer protocols.
Home-page: https://github.com/ustudio/storage
License: Apache-2.0
Author: uStudio Developers
Author-email: dev@ustudio.com
Requires-Python: >=3.9,<4.0
Classifier: License :: OSI Approved :: Apache Software License
Classifier: Programming Language :: Python :: 3
Classifier: Programming Language :: Python :: 3.9
Classifier: Programming Language :: Python :: 3.10
Classifier: Programming Language :: Python :: 3.11
Classifier: Programming Language :: Python :: 3.12
Classifier: Programming Language :: Python :: 3.13
Requires-Dist: boto3 (>=1.35.68,<2.0.0)
Requires-Dist: google-cloud-storage (>=2.18.2,<3.0.0)
Requires-Dist: keystoneauth1 (>=5.9.0,<6.0.0)
Requires-Dist: python-swiftclient (>=4.6.0,<5.0.0)
Project-URL: Repository, https://github.com/ustudio/storage
